CONTRIBUTORS.rst
COPYING.txt
MANIFEST.in
README.rst
THANKS.rst
setup.cfg
setup.py
doc/Makefile
doc/build/doctrees/environment.pickle
doc/build/doctrees/index.doctree
doc/build/doctrees/api/node.doctree
doc/build/doctrees/api/partition.doctree
doc/build/doctrees/api/statistics.doctree
doc/build/doctrees/dev/decisions.doctree
doc/build/doctrees/dev/github.doctree
doc/build/doctrees/dev/index.doctree
doc/build/doctrees/dev/licensing.doctree
doc/build/doctrees/dev/versioning.doctree
doc/build/doctrees/examples/general.doctree
doc/build/doctrees/examples/index.doctree
doc/build/html/.buildinfo
doc/build/html/.nojekyll
doc/build/html/genindex.html
doc/build/html/index.html
doc/build/html/objects.inv
doc/build/html/search.html
doc/build/html/searchindex.js
doc/build/html/_sources/index.txt
doc/build/html/_sources/api/node.txt
doc/build/html/_sources/api/partition.txt
doc/build/html/_sources/api/statistics.txt
doc/build/html/_sources/dev/decisions.txt
doc/build/html/_sources/dev/github.txt
doc/build/html/_sources/dev/index.txt
doc/build/html/_sources/dev/licensing.txt
doc/build/html/_sources/dev/versioning.txt
doc/build/html/_sources/examples/general.txt
doc/build/html/_sources/examples/index.txt
doc/build/html/_static/ajax-loader.gif
doc/build/html/_static/alabaster.css
doc/build/html/_static/basic.css
doc/build/html/_static/comment-bright.png
doc/build/html/_static/comment-close.png
doc/build/html/_static/comment.png
doc/build/html/_static/custom.css
doc/build/html/_static/doctools.js
doc/build/html/_static/down-pressed.png
doc/build/html/_static/down.png
doc/build/html/_static/file.png
doc/build/html/_static/jquery-1.11.1.js
doc/build/html/_static/jquery.js
doc/build/html/_static/minus.png
doc/build/html/_static/plus.png
doc/build/html/_static/pygments.css
doc/build/html/_static/pyslurm-logo.png
doc/build/html/_static/searchtools.js
doc/build/html/_static/underscore-1.3.1.js
doc/build/html/_static/underscore.js
doc/build/html/_static/up-pressed.png
pyslurm.egg-info/PKG-INFO
pyslurm.egg-info/SOURCES.txt
pyslurm.egg-info/dependency_links.txt
pyslurm.egg-info/requires.txt
pyslurm.egg-info/top_level.txt
